seamapi/__init__.py
seamapi/client.py
seamapi/core/__init__.py
seamapi/core/api_error.py
seamapi/core/client_wrapper.py
seamapi/core/datetime_utils.py
seamapi/core/jsonable_encoder.py
seamapi/core/remove_none_from_dict.py
seamapi/environment.py
seamapi/errors/__init__.py
seamapi/errors/bad_request_error.py
seamapi/errors/unauthorized_error.py
seamapi/py.typed
seamapi/resources/__init__.py
seamapi/resources/access_codes/__init__.py
seamapi/resources/access_codes/client.py
seamapi/resources/access_codes/resources/__init__.py
seamapi/resources/access_codes/resources/simulate/__init__.py
seamapi/resources/access_codes/resources/simulate/client.py
seamapi/resources/access_codes/resources/unmanaged/__init__.py
seamapi/resources/access_codes/resources/unmanaged/client.py
seamapi/resources/action_attempts/__init__.py
seamapi/resources/action_attempts/client.py
seamapi/resources/client_sessions/__init__.py
seamapi/resources/client_sessions/client.py
seamapi/resources/connect_webviews/__init__.py
seamapi/resources/connect_webviews/client.py
seamapi/resources/connected_accounts/__init__.py
seamapi/resources/connected_accounts/client.py
seamapi/resources/devices/__init__.py
seamapi/resources/devices/client.py
seamapi/resources/devices/resources/__init__.py
seamapi/resources/devices/resources/unmanaged/__init__.py
seamapi/resources/devices/resources/unmanaged/client.py
seamapi/resources/events/__init__.py
seamapi/resources/events/client.py
seamapi/resources/health/__init__.py
seamapi/resources/health/client.py
seamapi/resources/health/resources/__init__.py
seamapi/resources/health/resources/service/__init__.py
seamapi/resources/health/resources/service/client.py
seamapi/resources/locks/__init__.py
seamapi/resources/locks/client.py
seamapi/resources/noise_sensors/__init__.py
seamapi/resources/noise_sensors/client.py
seamapi/resources/noise_sensors/resources/__init__.py
seamapi/resources/noise_sensors/resources/noise_thresholds/__init__.py
fern_seam-0.1.3.dist-info/METADATA
fern_seam-0.1.3.dist-info/WHEEL
fern_seam-0.1.3.dist-info/RECORD
